awslambdalocal/__init__.py
awslambdalocal/__main__.py
awslambdalocal/context.py
awslambdalocal/event.py
awslambdalocal/loader.py
awslambdalocal/main.py
awslambdalocal/server.py
awslambdalocal/timeout.py
awslambdalocal-1.0.9.dist-info/LICENSE
awslambdalocal-1.0.9.dist-info/WHEEL
awslambdalocal-1.0.9.dist-info/METADATA
awslambdalocal-1.0.9.dist-info/RECORD
