Metadata-Version: 2.1
Name: awslambdalocal
Version: 1.0.9
Summary: A tool to simulate running an AWS Lambda locally
License: MIT
Author: Miqueias BRS
Author-email: miqueias@capybaracode.com.br
Requires-Python: >=3.8,<4.0
Classifier: License :: OSI Approved :: MIT License
Classifier: Programming Language :: Python :: 3
Classifier: Programming Language :: Python :: 3.10
Classifier: Programming Language :: Python :: 3.8
Classifier: Programming Language :: Python :: 3.9
Requires-Dist: python-dotenv (>=0.19.2,<0.20.0)
